metabograph/__init__.py
metabograph/cache.py
metabograph/common.py
metabograph/config.py
metabograph/exception.py
metabograph/fuseki.py
metabograph/logging.py
metabograph/main.py
metabograph/owl.py
metabograph/sparql.py
metabograph/utils.py
metabograph/version.py
metabograph/biopax/__init__.py
metabograph/biopax/graph_generator.py
metabograph/biopax/protein.py
metabograph/biopax/query_manager.py
metabograph/uniprot/__init__.py
metabograph/uniprot/id_mapping.py
metabograph-2024.5.dist-info/METADATA
metabograph-2024.5.dist-info/WHEEL
metabograph-2024.5.dist-info/entry_points.txt
metabograph-2024.5.dist-info/licenses/LICENSE.txt
metabograph-2024.5.dist-info/RECORD
