Metadata-Version: 2.3
Name: Metabograph
Version: 2024.5
Summary: Build metabolic graphs from online databases.
Project-URL: Homepage, https://gitlab.inria.fr/jrye/metabograph
Project-URL: Source, https://gitlab.inria.fr/jrye/metabograph.git
Project-URL: Documentation, https://jrye.gitlabpages.inria.fr/metabograph
Project-URL: Issues, https://gitlab.inria.fr/jrye/metabograph/-/issues
Author-email: Jan-Michael Rye <jan-michael.rye@inria.fr>, Nicolas Simon <nicolas.simon@inria.fr>
License: MIT License
Classifier: License :: OSI Approved :: MIT License
Classifier: Operating System :: OS Independent
Classifier: Programming Language :: Python :: 3
Requires-Python: >=3.6
Requires-Dist: dataclass-documenter
Requires-Dist: networkx
Requires-Dist: owlready2
Requires-Dist: pandas
Requires-Dist: pyxdg
Requires-Dist: pyyaml
Requires-Dist: rdflib
Requires-Dist: requests
Requires-Dist: sparqlwrapper
Requires-Dist: tqdm
Requires-Dist: uniprot-id-mapping
Provides-Extra: extra
Requires-Dist: tabulate; extra == 'extra'
